dl_interview/__init__.py
dl_interview/core.py
dl_interview/log.py
dl_interview/server.py
dl_interview-0.1.1.dist-info/METADATA
dl_interview-0.1.1.dist-info/WHEEL
dl_interview-0.1.1.dist-info/top_level.txt
dl_interview-0.1.1.dist-info/RECORD
